datadoc_model/__init__.py
datadoc_model/datadoc_base_model.py
datadoc_model/model.py
datadoc_model/py.typed
datadoc_model/all_optional/__init__.py
datadoc_model/all_optional/model.py
datadoc_model/all_optional/py.typed
datadoc_model/required/__init__.py
datadoc_model/required/model.py
datadoc_model/required/py.typed
ssb_datadoc_model-8.0.3.dist-info/METADATA
ssb_datadoc_model-8.0.3.dist-info/WHEEL
ssb_datadoc_model-8.0.3.dist-info/RECORD
