Metadata-Version: 2.4
Name: ssb-datadoc-model
Version: 8.0.3
Summary: Data Model for use in Statistics Norway's Metadata system
Project-URL: Homepage, https://github.com/statisticsnorway/ssb-datadoc-model
Project-URL: Repository, https://github.com/statisticsnorway/ssb-datadoc-model
Project-URL: Changelog, https://github.com/statisticsnorway/ssb-datadoc-model/releases
Author-email: Statistics Norway <metadata@ssb.no>
License-Expression: MIT
Requires-Python: >=3.10
Requires-Dist: pydantic>=2.5.2
